lektor_jupyter.py
setup.py
lektor_jupyter.egg-info/PKG-INFO
lektor_jupyter.egg-info/SOURCES.txt
lektor_jupyter.egg-info/dependency_links.txt
lektor_jupyter.egg-info/entry_points.txt
lektor_jupyter.egg-info/requires.txt
lektor_jupyter.egg-info/top_level.txt