Metadata-Version: 1.0
Name: lektor-jupyter
Version: 0.1
Summary: Embed Jupyter notebooks in Lektor pages
Home-page: http://github.com/baldwint/lektor-jupyter
Author: Thomas Baldwin
Author-email: tkb@sent.com
License: MIT
Platform: UNKNOWN
